wzk/__init__.py
wzk/ds.py
wzk/luna.py
wzk/mail.py
wzk/nlp.py
wzk/os.py
wzk/par_match.py
wzk/parser.py
wzk/utils.py
wzk/autograd/__init__.py
wzk/autograd/functional.py
wzk/autograd/thing.py
wzk/english/__init__.py
wzk/english/english.py
wzk/english/vocabulary.py
wzk/games/__init__.py
wzk/games/flight_game.py
wzk/games/game2048.py
wzk/games/mahjong.py
wzk/games/mine_sweeper.py
wzk/games/pokemon.py
wzk/games/texas_poker.py
wzk/oo2020/__init__.py
wzk/oo2020/beatmatch.py
wzk/oo2020/dataMake.py
wzk/oo2020/derivative.py
wzk/oo2020/elevator.py
wzk/oo2020/jml.py
wzk/oo2020/model.py
wzk/oo2020/randomUmlMake.py
wzk/oo2020/setting.py
wzk/oo2020/uml.py
wzk/vocab/__init__.py
wzk/vocab/vocab.py
wzk/vocab/vocabulary.py
wzk-0.1.5.dist-info/METADATA
wzk-0.1.5.dist-info/WHEEL
wzk-0.1.5.dist-info/top_level.txt
wzk-0.1.5.dist-info/RECORD
