Metadata-Version: 2.1
Name: wzk
Version: 0.1.5
Summary: wzk's library
Home-page: https://github.com/wzk1015/wzk-pypi-package
Author: zhaokai wang
Author-email: self@wzk.plus
License: UNKNOWN
Platform: UNKNOWN
